Metadata-Version: 2.4
Name: x4c
Version: 2025.10.13
Summary: x4c: Xarray for CESM
Home-page: https://github.com/NCAR/x4c
Author: Feng Zhu
Author-email: fengzhu@ucar.edu
License: Apache-2.0
Keywords: Xarray,CESM,Climate Data Analysis and Visualization
Classifier: Natural Language :: English
Classifier: Programming Language :: Python :: 3.12
Classifier: Programming Language :: Python :: 3.13
License-File: LICENSE
Requires-Dist: netCDF4
Requires-Dist: xarray
Requires-Dist: dask
Requires-Dist: nc-time-axis
Requires-Dist: colorama
Requires-Dist: tqdm
Requires-Dist: mpi4py
Dynamic: author
Dynamic: author-email
Dynamic: classifier
Dynamic: description
Dynamic: description-content-type
Dynamic: home-page
Dynamic: keywords
Dynamic: license
Dynamic: license-file
Dynamic: requires-dist
Dynamic: summary
